neispy/__init__.py
neispy/client.py
neispy/error.py
neispy/http.py
neispy/py.typed
neispy/sync.pyi
neispy/utils.py
neispy/domain/__init__.py
neispy/domain/abc.py
neispy/domain/acainstiinfo.py
neispy/domain/classinfo.py
neispy/domain/elstimetable.py
neispy/domain/histimetable.py
neispy/domain/mealservicedietinfo.py
neispy/domain/mistimetable.py
neispy/domain/schoolinfo.py
neispy/domain/schoolmajorinfo.py
neispy/domain/schoolschedule.py
neispy/domain/schulaflcoinfo.py
neispy/domain/spstimetable.py
neispy/domain/ticlrminfo.py
neispy/params/__init__.py
neispy/params/abc.py
neispy/params/acainstiinfo.py
neispy/params/classinfo.py
neispy/params/meal.py
neispy/params/schoolinfo.py
neispy/params/schoolmajorinfo.py
neispy/params/schoolschedule.py
neispy/params/schulaflcoinfo.py
neispy/params/ticlrminfo.py
neispy/params/timetable.py
neispy/types/__init__.py
neispy/types/acainstiinfo.py
neispy/types/base.py
neispy/types/classinfo.py
neispy/types/elstimetable.py
neispy/types/histimetable.py
neispy/types/mealservicedietinfo.py
neispy/types/mistimetable.py
neispy/types/schoolinfo.py
neispy/types/schoolmajorinfo.py
neispy/types/schoolschedule.py
neispy/types/schulaflcoinfo.py
neispy/types/spstimetable.py
neispy/types/ticlrminfo.py
test/__init__.py
test/conftest.py
neispy-5.0.2.dist-info/LICENSE
neispy-5.0.2.dist-info/METADATA
neispy-5.0.2.dist-info/WHEEL
neispy-5.0.2.dist-info/top_level.txt
neispy-5.0.2.dist-info/RECORD
