Metadata-Version: 2.1
Name: neispy
Version: 5.0.2
Summary: open-neis-api wrapping with aiohttp
Home-page: https://github.com/SaidBySolo/neispy
Author: Ryu ju heon
Author-email: SaidBySolo@gmail.com
License: MIT
Classifier: License :: OSI Approved :: MIT License
Classifier: Operating System :: OS Independent
Requires-Python: >=3.6
License-File: LICENSE
Requires-Dist: aiohttp
Requires-Dist: typing-extensions
